{
    "filters": {
        "distance": {
            "min_m": 0.1,
            "max_m": 100.0,
            "enabled": false
        },
        "roi": {
            "x_min": -10.0,
            "x_max": 10.0,
            "y_min": -10.0,
            "y_max": -0.1,
            "z_min": -5.0,
            "z_max": -0.1,
            "enabled": false
        },
        "sea_filter": {
            "sea_level_z": -0.6,
            "margin_m": 0.1,
            "enabled": false
        },
        "statistical_outlier": {
            "mean_k": 20,
            "stddev_mul": 1.0,
            "enabled": false
        },
        "voxel": {
            "leaf_size": 0.1,
            "enabled": false
        },
        "density": {
            "voxel_size": 0.3,
            "min_points": 3,
            "enabled": false
        },
        "motion": {
            "cell_size": 0.5,
            "threshold": 0.3,
            "output_static": true,
            "enabled": false
        }
    },
    "docking": {
        "nearest_region": {
            "sector_x_min": 0.1,
            "sector_x_max": 15.0,
            "sector_y_min": -15.0,
            "sector_y_max": -0.1,
            "sector_z_min": -5.0,
            "sector_z_max": -0.1,
            "percentile": 5.0,
            "enabled": true
        },
        "dock_edge": {
            "x_min": 0.1,
            "x_max": 10.0,
            "y_min": -10.0,
            "y_max": -0.1,
            "z_min": -5.0,
            "z_max": -0.1,
            "ransac_dist": 0.15,
            "enabled": true
        },
        "temporal": {
            "max_jump_m": 2.0,
            "enabled": true
        }
    },
    "udp": {
        "target_ip": "127.0.0.1",
        "target_port": 5000,
        "sensor_id": 3,
        "enabled": true
    }
}